{
  "breakpoints": {
    "375": {
      "name": "settings-name-section",
      "viewportWidth": 303,
      "width": 303,
      "height": 273,
      "bones": [
        [
          0,
          0,
          37.4948,
          20,
          8
        ],
        [
          0,
          52,
          20.5446,
          19,
          8
        ],
        [
          0,
          79,
          100,
          42,
          10
        ],
        [
          0,
          145,
          21.3181,
          19,
          8
        ],
        [
          0,
          173,
          100,
          42,
          10
        ],
        [
          58.4674,
          239,
          41.5326,
          34,
          10
        ]
      ]
    },
    "640": {
      "name": "settings-name-section",
      "viewportWidth": 568,
      "width": 568,
      "height": 273,
      "bones": [
        [
          0,
          0,
          20.0017,
          20,
          8
        ],
        [
          0,
          52,
          10.9595,
          19,
          8
        ],
        [
          0,
          79,
          100,
          42,
          10
        ],
        [
          0,
          145,
          11.3721,
          19,
          8
        ],
        [
          0,
          173,
          100,
          42,
          10
        ],
        [
          77.8444,
          239,
          22.1556,
          34,
          10
        ]
      ]
    },
    "768": {
      "name": "settings-name-section",
      "viewportWidth": 440,
      "width": 440,
      "height": 273,
      "bones": [
        [
          0,
          0,
          25.8203,
          20,
          8
        ],
        [
          0,
          52,
          14.1477,
          19,
          8
        ],
        [
          0,
          79,
          100,
          42,
          10
        ],
        [
          0,
          145,
          14.6804,
          19,
          8
        ],
        [
          0,
          173,
          100,
          42,
          10
        ],
        [
          71.3991,
          239,
          28.6009,
          34,
          10
        ]
      ]
    },
    "1024": {
      "name": "settings-name-section",
      "viewportWidth": 424,
      "width": 424,
      "height": 287,
      "bones": [
        [
          0,
          0,
          26.7947,
          20,
          8
        ],
        [
          0,
          52,
          14.6816,
          19,
          8
        ],
        [
          0,
          79,
          100,
          42,
          10
        ],
        [
          0,
          145,
          15.2344,
          19,
          8
        ],
        [
          0,
          173,
          100,
          42,
          10
        ],
        [
          66.5463,
          239,
          33.4537,
          48,
          14
        ]
      ]
    },
    "1280": {
      "name": "settings-name-section",
      "viewportWidth": 680,
      "width": 680,
      "height": 287,
      "bones": [
        [
          0,
          0,
          16.7073,
          20,
          8
        ],
        [
          0,
          52,
          9.1544,
          19,
          8
        ],
        [
          0,
          79,
          100,
          42,
          10
        ],
        [
          0,
          145,
          9.4991,
          19,
          8
        ],
        [
          0,
          173,
          100,
          42,
          10
        ],
        [
          79.1406,
          239,
          20.8594,
          48,
          14
        ]
      ]
    },
    "1536": {
      "name": "settings-name-section",
      "viewportWidth": 936,
      "width": 936,
      "height": 287,
      "bones": [
        [
          0,
          0,
          12.1378,
          20,
          8
        ],
        [
          0,
          52,
          6.6506,
          19,
          8
        ],
        [
          0,
          79,
          100,
          42,
          10
        ],
        [
          0,
          145,
          6.901,
          19,
          8
        ],
        [
          0,
          173,
          100,
          42,
          10
        ],
        [
          84.8458,
          239,
          15.1542,
          48,
          14
        ]
      ]
    }
  },
  "_hash": "7d868fd09828d218e40cd1296e6adac1"
}